inventa/__init__.py
inventa/endless_timer_task.py
inventa/inventa.py
inventa/rpc_call_request.py
inventa/rpc_call_response.py
inventa/service_descriptor.py
inventa/utils.py
inventa-0.0a15.dist-info/LICENSE
inventa-0.0a15.dist-info/METADATA
inventa-0.0a15.dist-info/WHEEL
inventa-0.0a15.dist-info/top_level.txt
inventa-0.0a15.dist-info/RECORD
