Metadata-Version: 2.1
Name: inventa
Version: 0.0a15
Summary: A Python library for microservice registry and executing RPC (Remote Procedure Call) over Redis
Author: Adil Alper DALKIRAN
License: Apache 2.0
Project-URL: Homepage, https://github.com/adalkiran/py-inventa
Project-URL: Source, https://github.com/adalkiran/py-inventa
Project-URL: Bug Tracker, https://github.com/adalkiran/py-inventa/issues
Classifier: Programming Language :: Python :: 3
Classifier: License :: OSI Approved :: Apache Software License
Classifier: Development Status :: 2 - Pre-Alpha
Classifier: Intended Audience :: Developers
Classifier: Topic :: Software Development :: Libraries
Classifier: Topic :: Software Development :: Libraries :: Python Modules
Classifier: Topic :: System :: Distributed Computing
Classifier: Operating System :: OS Independent
Requires-Python: >=3.7
License-File: LICENSE
Requires-Dist: redis (>=4.3.4)
Requires-Dist: async-timeout (>=4.0.2)
